sinapsis_albumentations/src/sinapsis_albumentations/__init__.py
sinapsis_albumentations/src/sinapsis_albumentations/helpers/__init__.py
sinapsis_albumentations/src/sinapsis_albumentations/helpers/tags.py
sinapsis_albumentations/src/sinapsis_albumentations/templates/__init__.py
sinapsis_albumentations/src/sinapsis_albumentations/templates/albumentations_transforms.py
sinapsis_image_transforms-0.2.5.dist-info/licenses/LICENSE
sinapsis_image_transforms-0.2.5.dist-info/METADATA
sinapsis_image_transforms-0.2.5.dist-info/WHEEL
sinapsis_image_transforms-0.2.5.dist-info/top_level.txt
sinapsis_image_transforms-0.2.5.dist-info/RECORD
