Metadata-Version: 2.4
Name: sinapsis-image-transforms
Version: 0.2.5
Summary: Package to handle image transformations
Author-email: SinapsisAI <dev@sinapsis.tech>
Project-URL: Homepage, https://sinapsis.tech
Project-URL: Documentation, https://docs.sinapsis.tech/docs
Project-URL: Tutorials, https://docs.sinapsis.tech/tutorials
Project-URL: Repository, https://github.com/Sinapsis-AI/sinapsis-image-transforms.git
Requires-Python: >=3.10
License-File: LICENSE
Requires-Dist: sinapsis>=0.1.1
Provides-Extra: webapp-gradio
Requires-Dist: sinapsis[webapp]>=0.2.7; extra == "webapp-gradio"
Provides-Extra: dev
Requires-Dist: ruff>=0.8.3; extra == "dev"
Requires-Dist: pre-commit>=4.0.1; extra == "dev"
Provides-Extra: all
Requires-Dist: sinapsis-image-transforms[webapp-gradio]; extra == "all"
Requires-Dist: sinapsis-image-transforms[dev]; extra == "all"
Requires-Dist: sinapsis-albumentations; extra == "all"
Dynamic: license-file
